aioallay/__init__.py
aioallay/client.py
aioallay/types/AllayVersion.py
aioallay/types/AteStata.py
aioallay/types/BankCard.py
aioallay/types/BaseStata.py
aioallay/types/BlockStata.py
aioallay/types/CityOrder.py
aioallay/types/Command.py
aioallay/types/Donate.py
aioallay/types/FishStata.py
aioallay/types/GameProfile.py
aioallay/types/GameSession.py
aioallay/types/MobsStata.py
aioallay/types/NewProfileRequest.py
aioallay/types/Page.py
aioallay/types/PageData.py
aioallay/types/Rate.py
aioallay/types/RateRequest.py
aioallay/types/RateTop.py
aioallay/types/Server.py
aioallay/types/SetBioRequest.py
aioallay/types/SimpleMarket.py
aioallay/types/Skin.py
aioallay/types/TakeCityOrderResponse.py
aioallay/types/TopMessages.py
aioallay/types/User.py
aioallay/types/UserMesageStata.py
aioallay/types/UserShort.py
aioallay/types/UserTime.py
aioallay/types/__init__.py
aioallay/types/ws/LogsSecurity.py
aioallay/types/ws/__init__.py
aioallay-0.0.7.dist-info/licenses/LICENSE
aioallay-0.0.7.dist-info/METADATA
aioallay-0.0.7.dist-info/WHEEL
aioallay-0.0.7.dist-info/top_level.txt
aioallay-0.0.7.dist-info/RECORD
