Metadata-Version: 2.4
Name: AioAllay
Version: 0.0.7
Summary: Async client for Minecraft Bedrock Server API
Author-email: Yurii Sulima <yuriisulyma@gmail.com>
License-Expression: MIT
Project-URL: homepage, https://github.com/yurasulima/AioAllay
Project-URL: repository, https://github.com/yurasulima/AioAllay
Project-URL: documentation, https://github.com/yurasulima/AioAllay
Keywords: dangerous,library,python,minecraft,allay,bedrock,dangerous,mcapi
Classifier: Programming Language :: Python :: 3
Classifier: Operating System :: OS Independent
Requires-Python: >=3.10
License-File: LICENSE
Requires-Dist: aiohttp~=3.10.11
Requires-Dist: pydantic~=2.11.5
Dynamic: license-file
